MANIFEST.in
requirements.txt
setup.cfg
setup.py
Shaft.egg-info/PKG-INFO
Shaft.egg-info/SOURCES.txt
Shaft.egg-info/dependency_links.txt
Shaft.egg-info/entry_points.txt
Shaft.egg-info/not-zip-safe
Shaft.egg-info/requires.txt
Shaft.egg-info/top_level.txt
shaft/__about__.py
shaft/__about__.pyc
shaft/__init__.py
shaft/__init__.pyc
shaft/cli.py
shaft/cli.pyc
shaft/core.py
shaft/core.pyc
shaft/decorators.py
shaft/decorators.pyc
shaft/exceptions.py
shaft/exceptions.pyc
shaft/ext.py
shaft/ext.pyc
shaft/utils.py
shaft/utils.pyc
shaft/__pycache__/__about__.cpython-35.pyc
shaft/__pycache__/__about__.cpython-36.pyc
shaft/__pycache__/__init__.cpython-35.pyc
shaft/__pycache__/__init__.cpython-36.pyc
shaft/__pycache__/cli.cpython-35.pyc
shaft/__pycache__/cli.cpython-36.pyc
shaft/__pycache__/core.cpython-35.pyc
shaft/__pycache__/core.cpython-36.pyc
shaft/__pycache__/decorators.cpython-35.pyc
shaft/__pycache__/decorators.cpython-36.pyc
shaft/__pycache__/exceptions.cpython-35.pyc
shaft/__pycache__/exceptions.cpython-36.pyc
shaft/__pycache__/ext.cpython-35.pyc
shaft/__pycache__/ext.cpython-36.pyc
shaft/__pycache__/utils.cpython-35.pyc
shaft/__pycache__/utils.cpython-36.pyc
shaft/contrib/.DS_Store
shaft/contrib/__init__.py
shaft/contrib/__init__.pyc
shaft/contrib/app_option.py
shaft/contrib/app_option.pyc
shaft/contrib/__pycache__/__init__.cpython-35.pyc
shaft/contrib/__pycache__/__init__.cpython-36.pyc
shaft/contrib/auth/__init__.py
shaft/contrib/auth/__init__.pyc
shaft/contrib/auth/decorators.py
shaft/contrib/auth/decorators.pyc
shaft/contrib/auth/exceptions.py
shaft/contrib/auth/exceptions.pyc
shaft/contrib/auth/models.py
shaft/contrib/auth/models.pyc
shaft/contrib/auth/signals.py
shaft/contrib/auth/signals.pyc
shaft/contrib/static/assets.yml
shaft/contrib/static/Shaft/jquery-oembed/jquery.oembed.css
shaft/contrib/static/Shaft/jquery-oembed/jquery.oembed.js
shaft/contrib/static/Shaft/lib/css/_mixins.scss
shaft/contrib/static/Shaft/lib/css/shaft.css
shaft/contrib/static/Shaft/lib/css/shaft.scss
shaft/contrib/static/Shaft/lib/js/shaft.js
shaft/contrib/static/Shaft/vendor/bootstrap-social/bootstrap-social.css
shaft/contrib/static/Shaft/vendor/bootstrap/css/bootstrap-theme.css
